system_features/__init__.py
system_features/hardware_info.py
system_features-0.1.0.dist-info/METADATA
system_features-0.1.0.dist-info/WHEEL
system_features-0.1.0.dist-info/top_level.txt
system_features-0.1.0.dist-info/RECORD
