Metadata-Version: 2.1
Name: system_features
Version: 0.1.0
Summary: A simple Python package
Author: Your Name
Requires-Python: >=3.6
Requires-Dist: psutil
Requires-Dist: GPUtil
